MSMetaEnhancer/__init__.py
MSMetaEnhancer/app.py
MSMetaEnhancer/libs/Annotator.py
MSMetaEnhancer/libs/Converter.py
MSMetaEnhancer/libs/Curator.py
MSMetaEnhancer/libs/__init__.py
MSMetaEnhancer/libs/converters/__init__.py
MSMetaEnhancer/libs/converters/compute/ComputeConverter.py
MSMetaEnhancer/libs/converters/compute/RDKit.py
MSMetaEnhancer/libs/converters/compute/__init__.py
MSMetaEnhancer/libs/converters/web/BridgeDb.py
MSMetaEnhancer/libs/converters/web/CIR.py
MSMetaEnhancer/libs/converters/web/CTS.py
MSMetaEnhancer/libs/converters/web/IDSM.py
MSMetaEnhancer/libs/converters/web/PubChem.py
MSMetaEnhancer/libs/converters/web/WebConverter.py
MSMetaEnhancer/libs/converters/web/__init__.py
MSMetaEnhancer/libs/data/Data.py
MSMetaEnhancer/libs/data/DataFrame.py
MSMetaEnhancer/libs/data/Spectra.py
MSMetaEnhancer/libs/data/__init__.py
MSMetaEnhancer/libs/utils/ConverterBuilder.py
MSMetaEnhancer/libs/utils/Errors.py
MSMetaEnhancer/libs/utils/Generic.py
MSMetaEnhancer/libs/utils/Job.py
MSMetaEnhancer/libs/utils/LogRecord.py
MSMetaEnhancer/libs/utils/Logger.py
MSMetaEnhancer/libs/utils/Metrics.py
MSMetaEnhancer/libs/utils/Monitor.py
MSMetaEnhancer/libs/utils/Throttler.py
MSMetaEnhancer/libs/utils/__init__.py
msmetaenhancer-0.4.1.dist-info/LICENSE
msmetaenhancer-0.4.1.dist-info/METADATA
msmetaenhancer-0.4.1.dist-info/WHEEL
msmetaenhancer-0.4.1.dist-info/RECORD
