Metadata-Version: 2.3
Name: msmetaenhancer
Version: 0.4.1
Summary: Repository for tool that adds more annotations (e.g. SMILES, InChI, CAS number) to MSP files (Python version).
License: MIT
Author: Helge Hecht
Author-email: helge.hecht@recetox.muni.cz
Requires-Python: >=3.10,<3.13
Classifier: License :: OSI Approved :: MIT License
Classifier: Programming Language :: Python :: 3
Classifier: Programming Language :: Python :: 3.10
Classifier: Programming Language :: Python :: 3.11
Classifier: Programming Language :: Python :: 3.12
Requires-Dist: aiocircuitbreaker (>=2.0.0,<3.0.0)
Requires-Dist: aiohttp (>=3.9.3,<4.0.0)
Requires-Dist: asyncstdlib (>=3.12.0,<4.0.0)
Requires-Dist: frozendict (>=2.4.0,<3.0.0)
Requires-Dist: matchms (>=0.28.2)
Requires-Dist: multidict (>=6.0.5,<7.0.0)
Requires-Dist: openpyxl (>=3.1.2,<4.0.0)
Requires-Dist: pandas (>=2.2.1,<3.0.0)
Requires-Dist: rdkit (>=2024.3.5,<2025.0.0)
Requires-Dist: requests (>=2.31.0,<3.0.0)
Requires-Dist: scipy (>=1.12.0,<2.0.0)
Requires-Dist: tabulate (>=0.9.0,<0.10.0)
Requires-Dist: twine (>=5.0.0,<6.0.0)
